Workbook

Sheet Hoja1
A2: Cantón | C2: Region
A3: Delegación
A5: Participacion
A6: DISTRITO | G6: ¿Cuál es la relación con la zona?
A7: Distrito | B7: Porcentaje | C7: Total | D7: Comercio | E7: Comunidad | G7: Relación | H7: Porcentaje | I7: Comunidad
B8: =(C8/$C$24)*1 -> #DIV/0! | C8: =SUM(D8:E8) -> 0 | G8: Estudio en la zona | H8: =(I8/$I$12)*1 -> #DIV/0!
B9: =(C9/$C$24)*1 -> #DIV/0! | C9: =SUM(D9:E9) -> 0 | G9: Trabajo en la zona | H9: =(I9/$I$12)*1 -> #DIV/0!
B10: =(C10/$C$24)*1 -> #DIV/0! | C10: =SUM(D10:E10) -> 0 | G10: Visito la zona | H10: =(I10/$I$12)*1 -> #DIV/0!
B11: =(C11/$C$24)*1 -> #DIV/0! | C11: =SUM(D11:E11) -> 0 | G11: Vivo en la zona | H11: =(I11/$I$12)*1 -> #DIV/0!
B12: =(C12/$C$24)*1 -> #DIV/0! | C12: =SUM(D12:E12) -> 0 | H12: =SUM(H8:H11) -> #DIV/0! | I12: =SUM(I8:I11) -> 0
B13: =(C13/$C$24)*1 -> #DIV/0! | C13: =SUM(D13:E13) -> 0
B14: =(C14/$C$24)*1 -> #DIV/0! | C14: =SUM(D14:E14) -> 0
B15: =(C15/$C$24)*1 -> #DIV/0! | C15: =SUM(D15:E15) -> 0
B16: =(C16/$C$24)*1 -> #DIV/0! | C16: =SUM(D16:E16) -> 0
B17: =(C17/$C$24)*1 -> #DIV/0! | C17: =SUM(D17:E17) -> 0
B18: =(C18/$C$24)*1 -> #DIV/0! | C18: =SUM(D18:E18) -> 0
B19: =(C19/$C$24)*1 -> #DIV/0! | C19: =SUM(D19:E19) -> 0
B20: =(C20/$C$24)*1 -> #DIV/0! | C20: =SUM(D20:E20) -> 0
B21: =(C21/$C$24)*1 -> #DIV/0! | C21: =SUM(D21:E21) -> 0
B22: =(C22/$C$24)*1 -> #DIV/0! | C22: =SUM(D22:E22) -> 0
B23: =(C23/$C$24)*1 -> #DIV/0! | C23: =SUM(D23:E23) -> 0
A24: Total | B24: =SUM(B8:B23) -> #DIV/0! | C24: =SUM(C8:C23) -> 0 | D24: =SUM(D8:D23) -> 0 | E24: =SUM(E8:E23) -> 0
A27: Participación por edad
D28: Comunidad | E28: Comercio | F28: FP
A29: De 18 a 29 | B29: =(C29/$C$34)*1 -> #DIV/0! | C29: =SUM(D29:F29) -> 0
A30: De 30 a 44 | B30: =(C30/$C$34)*1 -> #DIV/0! | C30: =SUM(D30:F30) -> 0
A31: De 45 a 64 | B31: =(C31/$C$34)*1 -> #DIV/0! | C31: =SUM(D31:F31) -> 0
A32: De 65 años o más | B32: =(C32/$C$34)*1 -> #DIV/0! | C32: =SUM(D32:F32) -> 0
A33: Vacio | B33: =(C33/$C$34)*1 -> #DIV/0! | C33: =SUM(D33:F33) -> 0
B34: =SUM(B29:B33) -> #DIV/0! | C34: =SUM(C29:C33) -> 0 | D34: =SUM(D29:D33) -> 0 | E34: =SUM(E29:E33) -> 0 | F34: =SUM(F29:F33) -> 0
A37: Escolaridad
D38: Comunidad | E38: Comercio | F38: FP
A39: Ninguna | B39: =(C39/$C$47)*1 -> #DIV/0! | C39: =SUM(D39:F39) -> 0
A40: Primaria | B40: =(C40/$C$47)*1 -> #DIV/0! | C40: =SUM(D40:F40) -> 0
A41: Primaria incompleta | B41: =(C41/$C$47)*1 -> #DIV/0! | C41: =SUM(D41:F41) -> 0
A42: Secundaria completa | B42: =(C42/$C$47)*1 -> #DIV/0! | C42: =SUM(D42:F42) -> 0
A43: Secundaria incompleta | B43: =(C43/$C$47)*1 -> #DIV/0! | C43: =SUM(D43:F43) -> 0
A44: Técnico | B44: =(C44/$C$47)*1 -> #DIV/0! | C44: =SUM(D44:F44) -> 0
A45: Universidad | B45: =(C45/$C$47)*1 -> #DIV/0! | C45: =SUM(D45:F45) -> 0
A46: Universidad incompleta | B46: =(C46/$C$47)*1 -> #DIV/0! | C46: =SUM(D46:F46) -> 0
B47: =SUM(B39:B46) -> #DIV/0! | C47: =SUM(C39:C46) -> 0 | D47: =SUM(D39:D46) -> 0 | E47: =SUM(E39:E46) -> 0 | F47: =SUM(F39:F46) -> 0
A50: Genero
D51: Comunidad | E51: Comercio | F51: FP
A52: Masculino | B52: =(C52/$C$55)*1 -> #DIV/0! | C52: =SUM(D52:F52) -> 0
A53: Femenino | B53: =(C53/$C$55)*1 -> #DIV/0! | C53: =SUM(D53:F53) -> 0
A54: LGBTQ+ | B54: =(C54/$C$55)*1 -> #DIV/0! | C54: =SUM(D54:F54) -> 0
B55: =SUM(B52:B54) -> #DIV/0! | C55: =SUM(C52:C54) -> 0 | D55: =SUM(D52:D54) -> 0 | E55: =SUM(E52:E54) -> 0 | F55: =SUM(F52:F54) -> 0
A58: Proceso Metodológico | C58: Encuestas
A59: Delegación | B59: Población | C59: Requeridas | D59: Realizadas
A60: San Ramón
A62: Proceso Metodológico | C62: Encuestas | E62: Comunidad | G62: Otras | I62: Encuestas
A63: Distrito | B63: Población | C63: Requeridas | D63: Realizadas | G63: Distrito | H63: Población | I63: Requeridas | J63: Realizadas
G64: Comercio
G65: Policial
A81: Fuentes
A82: Datos Pareto
A83: Comunidad
A84: Comercio
A85: Policial
A86: OPO
A87: SAE | C87: =B86+B87 -> 0
B88: =SUM(B83:B87) -> 0
A90: Pareto
A91: Descriptores
A92: Datos | B92: Registrados | C92: 20/80 | D92: TOTAL XLXS
A93: =B88 -> 0 | B93: =(D93-1) -> -1 | C93: =D118 -> 0
A95: Tabla Pareto
B96: Delitos | C96: Riesgos
A97: 1
A98: 2
A99: 3
A100: 4
A101: 5
A102: 6
A103: 7
A104: 8
A105: 9
A106: 10
A107: 11
A108: 12
... A116: 20
A117: 21 | D117: Sumatoria
A118: Total | B118: =COUNTIF(B97:B117, "*") -> 0 | C118: =COUNTIF(C97:C117, "*") -> 0 | D118: =SUM(B118:C118) -> 0
A119: Porcentajes | B119: =(B118/$D$118)*1 -> #DIV/0! | C119: =(C118/$D$118)*1 -> #DIV/0! | D119: =SUM(B119:C119) -> #DIV/0!
A122: MICMAC | G122: Resultados MIC-MAC
B123: Poder | C123: Conflicto | D123: Resultados | E123: Autonomas | G123: Poder | H123: Clasificacion | I123: Conflicto | J123: Clasificacion | K123: Riesgos S | L123: Delitos
G124: =B124 -> 0 | H124: {=IF( SUMPRODUCT(--( SUBSTITUTE(SUBSTITUTE(SUBSTITUTE(SUBSTITUTE(SUBSTITUTE(SUBSTITUTE(SUBSTITUTE( UPPER(TRIM(CLEAN(SUBSTITUTE(Hoja2!A$3:A$89,CHAR(160)," ")))), "Á","A"),"É","E"),"Í","I"),"Ó","O"),"Ú","U"),"Ü","U"),"Ñ","N") = SUBSTITUTE(SUBSTITUTE(SUBSTITUTE(SUBSTITUTE(SUBSTITUTE(SUBSTITUTE(SUBSTITUTE( UPPER(TRIM(CLEAN(SUBSTITUTE(G124,CHAR(160)," ")))), "Á","A"),"É","E"),"Í","I"),"Ó","O"),"Ú","U"),"Ü","U"),"Ñ","N") ))>0, "D", IF( SUMPRODUCT(--( SUBSTITUTE(SUBSTITUTE(SUBSTITUTE(SUBSTITUTE(SUBSTITUTE(SUBSTITUTE(SUBSTITUTE( UPPER(TRIM(CLEAN(SUBSTITUTE(Hoja2!A$92:A$154,CHAR(160)," ")))), "Á","A"),"É","E"),"Í","I"),"Ó","O"),"Ú","U"),"Ü","U"),"Ñ","N") = SUBSTITUTE(SUBSTITUTE(SUBSTITUTE(SUBSTITUTE(SUBSTITUTE(SUBSTITUTE(SUBSTITUTE( UPPER(TRIM(CLEAN(SUBSTITUTE(G124,CHAR(160)," ")))), "Á","A"),"É","E"),"Í","I"),"Ó","O"),"Ú","U"),"Ü","U"),"Ñ","N") ))>0, "R", "" ) )} | I124: {=C124:C140} -> 0 | J124: {=IF( SUMPRODUCT(--( SUBSTITUTE(SUBSTITUTE(SUBSTITUTE(SUBSTITUTE(SUBSTITUTE(SUBSTITUTE(SUBSTITUTE( UPPER(TRIM(CLEAN(SUBSTITUTE(Hoja2!A$3:A$89,CHAR(160)," ")))), "Á","A"),"É","E"),"Í","I"),"Ó","O"),"Ú","U"),"Ü","U"),"Ñ","N") = SUBSTITUTE(SUBSTITUTE(SUBSTITUTE(SUBSTITUTE(SUBSTITUTE(SUBSTITUTE(SUBSTITUTE( UPPER(TRIM(CLEAN(SUBSTITUTE(I124,CHAR(160)," ")))), "Á","A"),"É","E"),"Í","I"),"Ó","O"),"Ú","U"),"Ü","U"),"Ñ","N") ))>0, "D", IF( SUMPRODUCT(--( SUBSTITUTE(SUBSTITUTE(SUBSTITUTE(SUBSTITUTE(SUBSTITUTE(SUBSTITUTE(SUBSTITUTE( UPPER(TRIM(CLEAN(SUBSTITUTE(Hoja2!A$92:A$154,CHAR(160)," ")))), "Á","A"),"É","E"),"Í","I"),"Ó","O"),"Ú","U"),"Ü","U"),"Ñ","N") = SUBSTITUTE(SUBSTITUTE(SUBSTITUTE(SUBSTITUTE(SUBSTITUTE(SUBSTITUTE(SUBSTITUTE( UPPER(TRIM(CLEAN(SUBSTITUTE(I124,CHAR(160)," ")))), "Á","A"),"É","E"),"Í","I"),"Ó","O"),"Ú","U"),"Ü","U"),"Ñ","N") ))>0, "R", "" ) )}
G125: =B125 -> 0 | H125: {=IF( SUMPRODUCT(--( SUBSTITUTE(SUBSTITUTE(SUBSTITUTE(SUBSTITUTE(SUBSTITUTE(SUBSTITUTE(SUBSTITUTE( UPPER(TRIM(CLEAN(SUBSTITUTE(Hoja2!A$3:A$89,CHAR(160)," ")))), "Á","A"),"É","E"),"Í","I"),"Ó","O"),"Ú","U"),"Ü","U"),"Ñ","N") = SUBSTITUTE(SUBSTITUTE(SUBSTITUTE(SUBSTITUTE(SUBSTITUTE(SUBSTITUTE(SUBSTITUTE( UPPER(TRIM(CLEAN(SUBSTITUTE(G125,CHAR(160)," ")))), "Á","A"),"É","E"),"Í","I"),"Ó","O"),"Ú","U"),"Ü","U"),"Ñ","N") ))>0, "D", IF( SUMPRODUCT(--( SUBSTITUTE(SUBSTITUTE(SUBSTITUTE(SUBSTITUTE(SUBSTITUTE(SUBSTITUTE(SUBSTITUTE( UPPER(TRIM(CLEAN(SUBSTITUTE(Hoja2!A$92:A$154,CHAR(160)," ")))), "Á","A"),"É","E"),"Í","I"),"Ó","O"),"Ú","U"),"Ü","U"),"Ñ","N") = SUBSTITUTE(SUBSTITUTE(SUBSTITUTE(SUBSTITUTE(SUBSTITUTE(SUBSTITUTE(SUBSTITUTE( UPPER(TRIM(CLEAN(SUBSTITUTE(G125,CHAR(160)," ")))), "Á","A"),"É","E"),"Í","I"),"Ó","O"),"Ú","U"),"Ü","U"),"Ñ","N") ))>0, "R", "" ) )} | I125: 0 | J125: {=IF( SUMPRODUCT(--( SUBSTITUTE(SUBSTITUTE(SUBSTITUTE(SUBSTITUTE(SUBSTITUTE(SUBSTITUTE(SUBSTITUTE( UPPER(TRIM(CLEAN(SUBSTITUTE(Hoja2!A$3:A$89,CHAR(160)," ")))), "Á","A"),"É","E"),"Í","I"),"Ó","O"),"Ú","U"),"Ü","U"),"Ñ","N") = SUBSTITUTE(SUBSTITUTE(SUBSTITUTE(SUBSTITUTE(SUBSTITUTE(SUBSTITUTE(SUBSTITUTE( UPPER(TRIM(CLEAN(SUBSTITUTE(I125,CHAR(160)," ")))), "Á","A"),"É","E"),"Í","I"),"Ó","O"),"Ú","U"),"Ü","U"),"Ñ","N") ))>0, "D", IF( SUMPRODUCT(--( SUBSTITUTE(SUBSTITUTE(SUBSTITUTE(SUBSTITUTE(SUBSTITUTE(SUBSTITUTE(SUBSTITUTE( UPPER(TRIM(CLEAN(SUBSTITUTE(Hoja2!A$92:A$154,CHAR(160)," ")))), "Á","A"),"É","E"),"Í","I"),"Ó","O"),"Ú","U"),"Ü","U"),"Ñ","N") = SUBSTITUTE(SUBSTITUTE(SUBSTITUTE(SUBSTITUTE(SUBSTITUTE(SUBSTITUTE(SUBSTITUTE( UPPER(TRIM(CLEAN(SUBSTITUTE(I125,CHAR(160)," ")))), "Á","A"),"É","E"),"Í","I"),"Ó","O"),"Ú","U"),"Ü","U"),"Ñ","N") ))>0, "R", "" ) )}
G126: =B126 -> 0 | H126: {=IF( SUMPRODUCT(--( SUBSTITUTE(SUBSTITUTE(SUBSTITUTE(SUBSTITUTE(SUBSTITUTE(SUBSTITUTE(SUBSTITUTE( UPPER(TRIM(CLEAN(SUBSTITUTE(Hoja2!A$3:A$89,CHAR(160)," ")))), "Á","A"),"É","E"),"Í","I"),"Ó","O"),"Ú","U"),"Ü","U"),"Ñ","N") = SUBSTITUTE(SUBSTITUTE(SUBSTITUTE(SUBSTITUTE(SUBSTITUTE(SUBSTITUTE(SUBSTITUTE( UPPER(TRIM(CLEAN(SUBSTITUTE(G126,CHAR(160)," ")))), "Á","A"),"É","E"),"Í","I"),"Ó","O"),"Ú","U"),"Ü","U"),"Ñ","N") ))>0, "D", IF( SUMPRODUCT(--( SUBSTITUTE(SUBSTITUTE(SUBSTITUTE(SUBSTITUTE(SUBSTITUTE(SUBSTITUTE(SUBSTITUTE( UPPER(TRIM(CLEAN(SUBSTITUTE(Hoja2!A$92:A$154,CHAR(160)," ")))), "Á","A"),"É","E"),"Í","I"),"Ó","O"),"Ú","U"),"Ü","U"),"Ñ","N") = SUBSTITUTE(SUBSTITUTE(SUBSTITUTE(SUBSTITUTE(SUBSTITUTE(SUBSTITUTE(SUBSTITUTE( UPPER(TRIM(CLEAN(SUBSTITUTE(G126,CHAR(160)," ")))), "Á","A"),"É","E"),"Í","I"),"Ó","O"),"Ú","U"),"Ü","U"),"Ñ","N") ))>0, "R", "" ) )} | I126: 0 | J126: {=IF( SUMPRODUCT(--( SUBSTITUTE(SUBSTITUTE(SUBSTITUTE(SUBSTITUTE(SUBSTITUTE(SUBSTITUTE(SUBSTITUTE( UPPER(TRIM(CLEAN(SUBSTITUTE(Hoja2!A$3:A$89,CHAR(160)," ")))), "Á","A"),"É","E"),"Í","I"),"Ó","O"),"Ú","U"),"Ü","U"),"Ñ","N") = SUBSTITUTE(SUBSTITUTE(SUBSTITUTE(SUBSTITUTE(SUBSTITUTE(SUBSTITUTE(SUBSTITUTE( UPPER(TRIM(CLEAN(SUBSTITUTE(I126,CHAR(160)," ")))), "Á","A"),"É","E"),"Í","I"),"Ó","O"),"Ú","U"),"Ü","U"),"Ñ","N") ))>0, "D", IF( SUMPRODUCT(--( SUBSTITUTE(SUBSTITUTE(SUBSTITUTE(SUBSTITUTE(SUBSTITUTE(SUBSTITUTE(SUBSTITUTE( UPPER(TRIM(CLEAN(SUBSTITUTE(Hoja2!A$92:A$154,CHAR(160)," ")))), "Á","A"),"É","E"),"Í","I"),"Ó","O"),"Ú","U"),"Ü","U"),"Ñ","N") = SUBSTITUTE(SUBSTITUTE(SUBSTITUTE(SUBSTITUTE(SUBSTITUTE(SUBSTITUTE(SUBSTITUTE( UPPER(TRIM(CLEAN(SUBSTITUTE(I126,CHAR(160)," ")))), "Á","A"),"É","E"),"Í","I"),"Ó","O"),"Ú","U"),"Ü","U"),"Ñ","N") ))>0, "R", "" ) )}
G127: =B127 -> 0 | H127: {=IF( SUMPRODUCT(--( SUBSTITUTE(SUBSTITUTE(SUBSTITUTE(SUBSTITUTE(SUBSTITUTE(SUBSTITUTE(SUBSTITUTE( UPPER(TRIM(CLEAN(SUBSTITUTE(Hoja2!A$3:A$89,CHAR(160)," ")))), "Á","A"),"É","E"),"Í","I"),"Ó","O"),"Ú","U"),"Ü","U"),"Ñ","N") = SUBSTITUTE(SUBSTITUTE(SUBSTITUTE(SUBSTITUTE(SUBSTITUTE(SUBSTITUTE(SUBSTITUTE( UPPER(TRIM(CLEAN(SUBSTITUTE(G127,CHAR(160)," ")))), "Á","A"),"É","E"),"Í","I"),"Ó","O"),"Ú","U"),"Ü","U"),"Ñ","N") ))>0, "D", IF( SUMPRODUCT(--( SUBSTITUTE(SUBSTITUTE(SUBSTITUTE(SUBSTITUTE(SUBSTITUTE(SUBSTITUTE(SUBSTITUTE( UPPER(TRIM(CLEAN(SUBSTITUTE(Hoja2!A$92:A$154,CHAR(160)," ")))), "Á","A"),"É","E"),"Í","I"),"Ó","O"),"Ú","U"),"Ü","U"),"Ñ","N") = SUBSTITUTE(SUBSTITUTE(SUBSTITUTE(SUBSTITUTE(SUBSTITUTE(SUBSTITUTE(SUBSTITUTE( UPPER(TRIM(CLEAN(SUBSTITUTE(G127,CHAR(160)," ")))), "Á","A"),"É","E"),"Í","I"),"Ó","O"),"Ú","U"),"Ü","U"),"Ñ","N") ))>0, "R", "" ) )} | I127: 0 | J127: {=IF( SUMPRODUCT(--( SUBSTITUTE(SUBSTITUTE(SUBSTITUTE(SUBSTITUTE(SUBSTITUTE(SUBSTITUTE(SUBSTITUTE( UPPER(TRIM(CLEAN(SUBSTITUTE(Hoja2!A$3:A$89,CHAR(160)," ")))), "Á","A"),"É","E"),"Í","I"),"Ó","O"),"Ú","U"),"Ü","U"),"Ñ","N") = SUBSTITUTE(SUBSTITUTE(SUBSTITUTE(SUBSTITUTE(SUBSTITUTE(SUBSTITUTE(SUBSTITUTE( UPPER(TRIM(CLEAN(SUBSTITUTE(I127,CHAR(160)," ")))), "Á","A"),"É","E"),"Í","I"),"Ó","O"),"Ú","U"),"Ü","U"),"Ñ","N") ))>0, "D", IF( SUMPRODUCT(--( SUBSTITUTE(SUBSTITUTE(SUBSTITUTE(SUBSTITUTE(SUBSTITUTE(SUBSTITUTE(SUBSTITUTE( UPPER(TRIM(CLEAN(SUBSTITUTE(Hoja2!A$92:A$154,CHAR(160)," ")))), "Á","A"),"É","E"),"Í","I"),"Ó","O"),"Ú","U"),"Ü","U"),"Ñ","N") = SUBSTITUTE(SUBSTITUTE(SUBSTITUTE(SUBSTITUTE(SUBSTITUTE(SUBSTITUTE(SUBSTITUTE( UPPER(TRIM(CLEAN(SUBSTITUTE(I127,CHAR(160)," ")))), "Á","A"),"É","E"),"Í","I"),"Ó","O"),"Ú","U"),"Ü","U"),"Ñ","N") ))>0, "R", "" ) )}
G128: =B128 -> 0 | H128: {=IF( SUMPRODUCT(--( SUBSTITUTE(SUBSTITUTE(SUBSTITUTE(SUBSTITUTE(SUBSTITUTE(SUBSTITUTE(SUBSTITUTE( UPPER(TRIM(CLEAN(SUBSTITUTE(Hoja2!A$3:A$89,CHAR(160)," ")))), "Á","A"),"É","E"),"Í","I"),"Ó","O"),"Ú","U"),"Ü","U"),"Ñ","N") = SUBSTITUTE(SUBSTITUTE(SUBSTITUTE(SUBSTITUTE(SUBSTITUTE(SUBSTITUTE(SUBSTITUTE( UPPER(TRIM(CLEAN(SUBSTITUTE(G128,CHAR(160)," ")))), "Á","A"),"É","E"),"Í","I"),"Ó","O"),"Ú","U"),"Ü","U"),"Ñ","N") ))>0, "D", IF( SUMPRODUCT(--( SUBSTITUTE(SUBSTITUTE(SUBSTITUTE(SUBSTITUTE(SUBSTITUTE(SUBSTITUTE(SUBSTITUTE( UPPER(TRIM(CLEAN(SUBSTITUTE(Hoja2!A$92:A$154,CHAR(160)," ")))), "Á","A"),"É","E"),"Í","I"),"Ó","O"),"Ú","U"),"Ü","U"),"Ñ","N") = SUBSTITUTE(SUBSTITUTE(SUBSTITUTE(SUBSTITUTE(SUBSTITUTE(SUBSTITUTE(SUBSTITUTE( UPPER(TRIM(CLEAN(SUBSTITUTE(G128,CHAR(160)," ")))), "Á","A"),"É","E"),"Í","I"),"Ó","O"),"Ú","U"),"Ü","U"),"Ñ","N") ))>0, "R", "" ) )} | I128: 0 | J128: {=IF( SUMPRODUCT(--( SUBSTITUTE(SUBSTITUTE(SUBSTITUTE(SUBSTITUTE(SUBSTITUTE(SUBSTITUTE(SUBSTITUTE( UPPER(TRIM(CLEAN(SUBSTITUTE(Hoja2!A$3:A$89,CHAR(160)," ")))), "Á","A"),"É","E"),"Í","I"),"Ó","O"),"Ú","U"),"Ü","U"),"Ñ","N") = SUBSTITUTE(SUBSTITUTE(SUBSTITUTE(SUBSTITUTE(SUBSTITUTE(SUBSTITUTE(SUBSTITUTE( UPPER(TRIM(CLEAN(SUBSTITUTE(I128,CHAR(160)," ")))), "Á","A"),"É","E"),"Í","I"),"Ó","O"),"Ú","U"),"Ü","U"),"Ñ","N") ))>0, "D", IF( SUMPRODUCT(--( SUBSTITUTE(SUBSTITUTE(SUBSTITUTE(SUBSTITUTE(SUBSTITUTE(SUBSTITUTE(SUBSTITUTE( UPPER(TRIM(CLEAN(SUBSTITUTE(Hoja2!A$92:A$154,CHAR(160)," ")))), "Á","A"),"É","E"),"Í","I"),"Ó","O"),"Ú","U"),"Ü","U"),"Ñ","N") = SUBSTITUTE(SUBSTITUTE(SUBSTITUTE(SUBSTITUTE(SUBSTITUTE(SUBSTITUTE(SUBSTITUTE( UPPER(TRIM(CLEAN(SUBSTITUTE(I128,CHAR(160)," ")))), "Á","A"),"É","E"),"Í","I"),"Ó","O"),"Ú","U"),"Ü","U"),"Ñ","N") ))>0, "R", "" ) )}
G129: =B129 -> 0 | H129: {=IF( SUMPRODUCT(--( SUBSTITUTE(SUBSTITUTE(SUBSTITUTE(SUBSTITUTE(SUBSTITUTE(SUBSTITUTE(SUBSTITUTE( UPPER(TRIM(CLEAN(SUBSTITUTE(Hoja2!A$3:A$89,CHAR(160)," ")))), "Á","A"),"É","E"),"Í","I"),"Ó","O"),"Ú","U"),"Ü","U"),"Ñ","N") = SUBSTITUTE(SUBSTITUTE(SUBSTITUTE(SUBSTITUTE(SUBSTITUTE(SUBSTITUTE(SUBSTITUTE( UPPER(TRIM(CLEAN(SUBSTITUTE(G129,CHAR(160)," ")))), "Á","A"),"É","E"),"Í","I"),"Ó","O"),"Ú","U"),"Ü","U"),"Ñ","N") ))>0, "D", IF( SUMPRODUCT(--( SUBSTITUTE(SUBSTITUTE(SUBSTITUTE(SUBSTITUTE(SUBSTITUTE(SUBSTITUTE(SUBSTITUTE( UPPER(TRIM(CLEAN(SUBSTITUTE(Hoja2!A$92:A$154,CHAR(160)," ")))), "Á","A"),"É","E"),"Í","I"),"Ó","O"),"Ú","U"),"Ü","U"),"Ñ","N") = SUBSTITUTE(SUBSTITUTE(SUBSTITUTE(SUBSTITUTE(SUBSTITUTE(SUBSTITUTE(SUBSTITUTE( UPPER(TRIM(CLEAN(SUBSTITUTE(G129,CHAR(160)," ")))), "Á","A"),"É","E"),"Í","I"),"Ó","O"),"Ú","U"),"Ü","U"),"Ñ","N") ))>0, "R", "" ) )} | I129: 0 | J129: {=IF( SUMPRODUCT(--( SUBSTITUTE(SUBSTITUTE(SUBSTITUTE(SUBSTITUTE(SUBSTITUTE(SUBSTITUTE(SUBSTITUTE( UPPER(TRIM(CLEAN(SUBSTITUTE(Hoja2!A$3:A$89,CHAR(160)," ")))), "Á","A"),"É","E"),"Í","I"),"Ó","O"),"Ú","U"),"Ü","U"),"Ñ","N") = SUBSTITUTE(SUBSTITUTE(SUBSTITUTE(SUBSTITUTE(SUBSTITUTE(SUBSTITUTE(SUBSTITUTE( UPPER(TRIM(CLEAN(SUBSTITUTE(I129,CHAR(160)," ")))), "Á","A"),"É","E"),"Í","I"),"Ó","O"),"Ú","U"),"Ü","U"),"Ñ","N") ))>0, "D", IF( SUMPRODUCT(--( SUBSTITUTE(SUBSTITUTE(SUBSTITUTE(SUBSTITUTE(SUBSTITUTE(SUBSTITUTE(SUBSTITUTE( UPPER(TRIM(CLEAN(SUBSTITUTE(Hoja2!A$92:A$154,CHAR(160)," ")))), "Á","A"),"É","E"),"Í","I"),"Ó","O"),"Ú","U"),"Ü","U"),"Ñ","N") = SUBSTITUTE(SUBSTITUTE(SUBSTITUTE(SUBSTITUTE(SUBSTITUTE(SUBSTITUTE(SUBSTITUTE( UPPER(TRIM(CLEAN(SUBSTITUTE(I129,CHAR(160)," ")))), "Á","A"),"É","E"),"Í","I"),"Ó","O"),"Ú","U"),"Ü","U"),"Ñ","N") ))>0, "R", "" ) )}
G130: =B130 -> 0 | H130: {=IF( SUMPRODUCT(--( SUBSTITUTE(SUBSTITUTE(SUBSTITUTE(SUBSTITUTE(SUBSTITUTE(SUBSTITUTE(SUBSTITUTE( UPPER(TRIM(CLEAN(SUBSTITUTE(Hoja2!A$3:A$89,CHAR(160)," ")))), "Á","A"),"É","E"),"Í","I"),"Ó","O"),"Ú","U"),"Ü","U"),"Ñ","N") = SUBSTITUTE(SUBSTITUTE(SUBSTITUTE(SUBSTITUTE(SUBSTITUTE(SUBSTITUTE(SUBSTITUTE( UPPER(TRIM(CLEAN(SUBSTITUTE(G130,CHAR(160)," ")))), "Á","A"),"É","E"),"Í","I"),"Ó","O"),"Ú","U"),"Ü","U"),"Ñ","N") ))>0, "D", IF( SUMPRODUCT(--( SUBSTITUTE(SUBSTITUTE(SUBSTITUTE(SUBSTITUTE(SUBSTITUTE(SUBSTITUTE(SUBSTITUTE( UPPER(TRIM(CLEAN(SUBSTITUTE(Hoja2!A$92:A$154,CHAR(160)," ")))), "Á","A"),"É","E"),"Í","I"),"Ó","O"),"Ú","U"),"Ü","U"),"Ñ","N") = SUBSTITUTE(SUBSTITUTE(SUBSTITUTE(SUBSTITUTE(SUBSTITUTE(SUBSTITUTE(SUBSTITUTE( UPPER(TRIM(CLEAN(SUBSTITUTE(G130,CHAR(160)," ")))), "Á","A"),"É","E"),"Í","I"),"Ó","O"),"Ú","U"),"Ü","U"),"Ñ","N") ))>0, "R", "" ) )} | I130: 0 | J130: {=IF( SUMPRODUCT(--( SUBSTITUTE(SUBSTITUTE(SUBSTITUTE(SUBSTITUTE(SUBSTITUTE(SUBSTITUTE(SUBSTITUTE( UPPER(TRIM(CLEAN(SUBSTITUTE(Hoja2!A$3:A$89,CHAR(160)," ")))), "Á","A"),"É","E"),"Í","I"),"Ó","O"),"Ú","U"),"Ü","U"),"Ñ","N") = SUBSTITUTE(SUBSTITUTE(SUBSTITUTE(SUBSTITUTE(SUBSTITUTE(SUBSTITUTE(SUBSTITUTE( UPPER(TRIM(CLEAN(SUBSTITUTE(I130,CHAR(160)," ")))), "Á","A"),"É","E"),"Í","I"),"Ó","O"),"Ú","U"),"Ü","U"),"Ñ","N") ))>0, "D", IF( SUMPRODUCT(--( SUBSTITUTE(SUBSTITUTE(SUBSTITUTE(SUBSTITUTE(SUBSTITUTE(SUBSTITUTE(SUBSTITUTE( UPPER(TRIM(CLEAN(SUBSTITUTE(Hoja2!A$92:A$154,CHAR(160)," ")))), "Á","A"),"É","E"),"Í","I"),"Ó","O"),"Ú","U"),"Ü","U"),"Ñ","N") = SUBSTITUTE(SUBSTITUTE(SUBSTITUTE(SUBSTITUTE(SUBSTITUTE(SUBSTITUTE(SUBSTITUTE( UPPER(TRIM(CLEAN(SUBSTITUTE(I130,CHAR(160)," ")))), "Á","A"),"É","E"),"Í","I"),"Ó","O"),"Ú","U"),"Ü","U"),"Ñ","N") ))>0, "R", "" ) )}
G131: =B131 -> 0 | H131: {=IF( SUMPRODUCT(--( SUBSTITUTE(SUBSTITUTE(SUBSTITUTE(SUBSTITUTE(SUBSTITUTE(SUBSTITUTE(SUBSTITUTE( UPPER(TRIM(CLEAN(SUBSTITUTE(Hoja2!A$3:A$89,CHAR(160)," ")))), "Á","A"),"É","E"),"Í","I"),"Ó","O"),"Ú","U"),"Ü","U"),"Ñ","N") = SUBSTITUTE(SUBSTITUTE(SUBSTITUTE(SUBSTITUTE(SUBSTITUTE(SUBSTITUTE(SUBSTITUTE( UPPER(TRIM(CLEAN(SUBSTITUTE(G131,CHAR(160)," ")))), "Á","A"),"É","E"),"Í","I"),"Ó","O"),"Ú","U"),"Ü","U"),"Ñ","N") ))>0, "D", IF( SUMPRODUCT(--( SUBSTITUTE(SUBSTITUTE(SUBSTITUTE(SUBSTITUTE(SUBSTITUTE(SUBSTITUTE(SUBSTITUTE( UPPER(TRIM(CLEAN(SUBSTITUTE(Hoja2!A$92:A$154,CHAR(160)," ")))), "Á","A"),"É","E"),"Í","I"),"Ó","O"),"Ú","U"),"Ü","U"),"Ñ","N") = SUBSTITUTE(SUBSTITUTE(SUBSTITUTE(SUBSTITUTE(SUBSTITUTE(SUBSTITUTE(SUBSTITUTE( UPPER(TRIM(CLEAN(SUBSTITUTE(G131,CHAR(160)," ")))), "Á","A"),"É","E"),"Í","I"),"Ó","O"),"Ú","U"),"Ü","U"),"Ñ","N") ))>0, "R", "" ) )} | I131: 0 | J131: {=IF( SUMPRODUCT(--( SUBSTITUTE(SUBSTITUTE(SUBSTITUTE(SUBSTITUTE(SUBSTITUTE(SUBSTITUTE(SUBSTITUTE( UPPER(TRIM(CLEAN(SUBSTITUTE(Hoja2!A$3:A$89,CHAR(160)," ")))), "Á","A"),"É","E"),"Í","I"),"Ó","O"),"Ú","U"),"Ü","U"),"Ñ","N") = SUBSTITUTE(SUBSTITUTE(SUBSTITUTE(SUBSTITUTE(SUBSTITUTE(SUBSTITUTE(SUBSTITUTE( UPPER(TRIM(CLEAN(SUBSTITUTE(I131,CHAR(160)," ")))), "Á","A"),"É","E"),"Í","I"),"Ó","O"),"Ú","U"),"Ü","U"),"Ñ","N") ))>0, "D", IF( SUMPRODUCT(--( SUBSTITUTE(SUBSTITUTE(SUBSTITUTE(SUBSTITUTE(SUBSTITUTE(SUBSTITUTE(SUBSTITUTE( UPPER(TRIM(CLEAN(SUBSTITUTE(Hoja2!A$92:A$154,CHAR(160)," ")))), "Á","A"),"É","E"),"Í","I"),"Ó","O"),"Ú","U"),"Ü","U"),"Ñ","N") = SUBSTITUTE(SUBSTITUTE(SUBSTITUTE(SUBSTITUTE(SUBSTITUTE(SUBSTITUTE(SUBSTITUTE( UPPER(TRIM(CLEAN(SUBSTITUTE(I131,CHAR(160)," ")))), "Á","A"),"É","E"),"Í","I"),"Ó","O"),"Ú","U"),"Ü","U"),"Ñ","N") ))>0, "R", "" ) )}
G132: =B132 -> 0 | H132: {=IF( SUMPRODUCT(--( SUBSTITUTE(SUBSTITUTE(SUBSTITUTE(SUBSTITUTE(SUBSTITUTE(SUBSTITUTE(SUBSTITUTE( UPPER(TRIM(CLEAN(SUBSTITUTE(Hoja2!A$3:A$89,CHAR(160)," ")))), "Á","A"),"É","E"),"Í","I"),"Ó","O"),"Ú","U"),"Ü","U"),"Ñ","N") = SUBSTITUTE(SUBSTITUTE(SUBSTITUTE(SUBSTITUTE(SUBSTITUTE(SUBSTITUTE(SUBSTITUTE( UPPER(TRIM(CLEAN(SUBSTITUTE(G132,CHAR(160)," ")))), "Á","A"),"É","E"),"Í","I"),"Ó","O"),"Ú","U"),"Ü","U"),"Ñ","N") ))>0, "D", IF( SUMPRODUCT(--( SUBSTITUTE(SUBSTITUTE(SUBSTITUTE(SUBSTITUTE(SUBSTITUTE(SUBSTITUTE(SUBSTITUTE( UPPER(TRIM(CLEAN(SUBSTITUTE(Hoja2!A$92:A$154,CHAR(160)," ")))), "Á","A"),"É","E"),"Í","I"),"Ó","O"),"Ú","U"),"Ü","U"),"Ñ","N") = SUBSTITUTE(SUBSTITUTE(SUBSTITUTE(SUBSTITUTE(SUBSTITUTE(SUBSTITUTE(SUBSTITUTE( UPPER(TRIM(CLEAN(SUBSTITUTE(G132,CHAR(160)," ")))), "Á","A"),"É","E"),"Í","I"),"Ó","O"),"Ú","U"),"Ü","U"),"Ñ","N") ))>0, "R", "" ) )} | I132: 0 | J132: {=IF( SUMPRODUCT(--( SUBSTITUTE(SUBSTITUTE(SUBSTITUTE(SUBSTITUTE(SUBSTITUTE(SUBSTITUTE(SUBSTITUTE( UPPER(TRIM(CLEAN(SUBSTITUTE(Hoja2!A$3:A$89,CHAR(160)," ")))), "Á","A"),"É","E"),"Í","I"),"Ó","O"),"Ú","U"),"Ü","U"),"Ñ","N") = SUBSTITUTE(SUBSTITUTE(SUBSTITUTE(SUBSTITUTE(SUBSTITUTE(SUBSTITUTE(SUBSTITUTE( UPPER(TRIM(CLEAN(SUBSTITUTE(I132,CHAR(160)," ")))), "Á","A"),"É","E"),"Í","I"),"Ó","O"),"Ú","U"),"Ü","U"),"Ñ","N") ))>0, "D", IF( SUMPRODUCT(--( SUBSTITUTE(SUBSTITUTE(SUBSTITUTE(SUBSTITUTE(SUBSTITUTE(SUBSTITUTE(SUBSTITUTE( UPPER(TRIM(CLEAN(SUBSTITUTE(Hoja2!A$92:A$154,CHAR(160)," ")))), "Á","A"),"É","E"),"Í","I"),"Ó","O"),"Ú","U"),"Ü","U"),"Ñ","N") = SUBSTITUTE(SUBSTITUTE(SUBSTITUTE(SUBSTITUTE(SUBSTITUTE(SUBSTITUTE(SUBSTITUTE( UPPER(TRIM(CLEAN(SUBSTITUTE(I132,CHAR(160)," ")))), "Á","A"),"É","E"),"Í","I"),"Ó","O"),"Ú","U"),"Ü","U"),"Ñ","N") ))>0, "R", "" ) )}
G133: =B133 -> 0 | H133: {=IF( SUMPRODUCT(--( SUBSTITUTE(SUBSTITUTE(SUBSTITUTE(SUBSTITUTE(SUBSTITUTE(SUBSTITUTE(SUBSTITUTE( UPPER(TRIM(CLEAN(SUBSTITUTE(Hoja2!A$3:A$89,CHAR(160)," ")))), "Á","A"),"É","E"),"Í","I"),"Ó","O"),"Ú","U"),"Ü","U"),"Ñ","N") = SUBSTITUTE(SUBSTITUTE(SUBSTITUTE(SUBSTITUTE(SUBSTITUTE(SUBSTITUTE(SUBSTITUTE( UPPER(TRIM(CLEAN(SUBSTITUTE(G133,CHAR(160)," ")))), "Á","A"),"É","E"),"Í","I"),"Ó","O"),"Ú","U"),"Ü","U"),"Ñ","N") ))>0, "D", IF( SUMPRODUCT(--( SUBSTITUTE(SUBSTITUTE(SUBSTITUTE(SUBSTITUTE(SUBSTITUTE(SUBSTITUTE(SUBSTITUTE( UPPER(TRIM(CLEAN(SUBSTITUTE(Hoja2!A$92:A$154,CHAR(160)," ")))), "Á","A"),"É","E"),"Í","I"),"Ó","O"),"Ú","U"),"Ü","U"),"Ñ","N") = SUBSTITUTE(SUBSTITUTE(SUBSTITUTE(SUBSTITUTE(SUBSTITUTE(SUBSTITUTE(SUBSTITUTE( UPPER(TRIM(CLEAN(SUBSTITUTE(G133,CHAR(160)," ")))), "Á","A"),"É","E"),"Í","I"),"Ó","O"),"Ú","U"),"Ü","U"),"Ñ","N") ))>0, "R", "" ) )} | I133: 0 | J133: {=IF( SUMPRODUCT(--( SUBSTITUTE(SUBSTITUTE(SUBSTITUTE(SUBSTITUTE(SUBSTITUTE(SUBSTITUTE(SUBSTITUTE( UPPER(TRIM(CLEAN(SUBSTITUTE(Hoja2!A$3:A$89,CHAR(160)," ")))), "Á","A"),"É","E"),"Í","I"),"Ó","O"),"Ú","U"),"Ü","U"),"Ñ","N") = SUBSTITUTE(SUBSTITUTE(SUBSTITUTE(SUBSTITUTE(SUBSTITUTE(SUBSTITUTE(SUBSTITUTE( UPPER(TRIM(CLEAN(SUBSTITUTE(I133,CHAR(160)," ")))), "Á","A"),"É","E"),"Í","I"),"Ó","O"),"Ú","U"),"Ü","U"),"Ñ","N") ))>0, "D", IF( SUMPRODUCT(--( SUBSTITUTE(SUBSTITUTE(SUBSTITUTE(SUBSTITUTE(SUBSTITUTE(SUBSTITUTE(SUBSTITUTE( UPPER(TRIM(CLEAN(SUBSTITUTE(Hoja2!A$92:A$154,CHAR(160)," ")))), "Á","A"),"É","E"),"Í","I"),"Ó","O"),"Ú","U"),"Ü","U"),"Ñ","N") = SUBSTITUTE(SUBSTITUTE(SUBSTITUTE(SUBSTITUTE(SUBSTITUTE(SUBSTITUTE(SUBSTITUTE( UPPER(TRIM(CLEAN(SUBSTITUTE(I133,CHAR(160)," ")))), "Á","A"),"É","E"),"Í","I"),"Ó","O"),"Ú","U"),"Ü","U"),"Ñ","N") ))>0, "R", "" ) )}
G134: =B134 -> 0 | H134: {=IF( SUMPRODUCT(--( SUBSTITUTE(SUBSTITUTE(SUBSTITUTE(SUBSTITUTE(SUBSTITUTE(SUBSTITUTE(SUBSTITUTE( UPPER(TRIM(CLEAN(SUBSTITUTE(Hoja2!A$3:A$89,CHAR(160)," ")))), "Á","A"),"É","E"),"Í","I"),"Ó","O"),"Ú","U"),"Ü","U"),"Ñ","N") = SUBSTITUTE(SUBSTITUTE(SUBSTITUTE(SUBSTITUTE(SUBSTITUTE(SUBSTITUTE(SUBSTITUTE( UPPER(TRIM(CLEAN(SUBSTITUTE(G134,CHAR(160)," ")))), "Á","A"),"É","E"),"Í","I"),"Ó","O"),"Ú","U"),"Ü","U"),"Ñ","N") ))>0, "D", IF( SUMPRODUCT(--( SUBSTITUTE(SUBSTITUTE(SUBSTITUTE(SUBSTITUTE(SUBSTITUTE(SUBSTITUTE(SUBSTITUTE( UPPER(TRIM(CLEAN(SUBSTITUTE(Hoja2!A$92:A$154,CHAR(160)," ")))), "Á","A"),"É","E"),"Í","I"),"Ó","O"),"Ú","U"),"Ü","U"),"Ñ","N") = SUBSTITUTE(SUBSTITUTE(SUBSTITUTE(SUBSTITUTE(SUBSTITUTE(SUBSTITUTE(SUBSTITUTE( UPPER(TRIM(CLEAN(SUBSTITUTE(G134,CHAR(160)," ")))), "Á","A"),"É","E"),"Í","I"),"Ó","O"),"Ú","U"),"Ü","U"),"Ñ","N") ))>0, "R", "" ) )} | I134: 0 | J134: {=IF( SUMPRODUCT(--( SUBSTITUTE(SUBSTITUTE(SUBSTITUTE(SUBSTITUTE(SUBSTITUTE(SUBSTITUTE(SUBSTITUTE( UPPER(TRIM(CLEAN(SUBSTITUTE(Hoja2!A$3:A$89,CHAR(160)," ")))), "Á","A"),"É","E"),"Í","I"),"Ó","O"),"Ú","U"),"Ü","U"),"Ñ","N") = SUBSTITUTE(SUBSTITUTE(SUBSTITUTE(SUBSTITUTE(SUBSTITUTE(SUBSTITUTE(SUBSTITUTE( UPPER(TRIM(CLEAN(SUBSTITUTE(I134,CHAR(160)," ")))), "Á","A"),"É","E"),"Í","I"),"Ó","O"),"Ú","U"),"Ü","U"),"Ñ","N") ))>0, "D", IF( SUMPRODUCT(--( SUBSTITUTE(SUBSTITUTE(SUBSTITUTE(SUBSTITUTE(SUBSTITUTE(SUBSTITUTE(SUBSTITUTE( UPPER(TRIM(CLEAN(SUBSTITUTE(Hoja2!A$92:A$154,CHAR(160)," ")))), "Á","A"),"É","E"),"Í","I"),"Ó","O"),"Ú","U"),"Ü","U"),"Ñ","N") = SUBSTITUTE(SUBSTITUTE(SUBSTITUTE(SUBSTITUTE(SUBSTITUTE(SUBSTITUTE(SUBSTITUTE( UPPER(TRIM(CLEAN(SUBSTITUTE(I134,CHAR(160)," ")))), "Á","A"),"É","E"),"Í","I"),"Ó","O"),"Ú","U"),"Ü","U"),"Ñ","N") ))>0, "R", "" ) )}
G135: =B135 -> 0 | H135: {=IF( SUMPRODUCT(--( SUBSTITUTE(SUBSTITUTE(SUBSTITUTE(SUBSTITUTE(SUBSTITUTE(SUBSTITUTE(SUBSTITUTE( UPPER(TRIM(CLEAN(SUBSTITUTE(Hoja2!A$3:A$89,CHAR(160)," ")))), "Á","A"),"É","E"),"Í","I"),"Ó","O"),"Ú","U"),"Ü","U"),"Ñ","N") = SUBSTITUTE(SUBSTITUTE(SUBSTITUTE(SUBSTITUTE(SUBSTITUTE(SUBSTITUTE(SUBSTITUTE( UPPER(TRIM(CLEAN(SUBSTITUTE(G135,CHAR(160)," ")))), "Á","A"),"É","E"),"Í","I"),"Ó","O"),"Ú","U"),"Ü","U"),"Ñ","N") ))>0, "D", IF( SUMPRODUCT(--( SUBSTITUTE(SUBSTITUTE(SUBSTITUTE(SUBSTITUTE(SUBSTITUTE(SUBSTITUTE(SUBSTITUTE( UPPER(TRIM(CLEAN(SUBSTITUTE(Hoja2!A$92:A$154,CHAR(160)," ")))), "Á","A"),"É","E"),"Í","I"),"Ó","O"),"Ú","U"),"Ü","U"),"Ñ","N") = SUBSTITUTE(SUBSTITUTE(SUBSTITUTE(SUBSTITUTE(SUBSTITUTE(SUBSTITUTE(SUBSTITUTE( UPPER(TRIM(CLEAN(SUBSTITUTE(G135,CHAR(160)," ")))), "Á","A"),"É","E"),"Í","I"),"Ó","O"),"Ú","U"),"Ü","U"),"Ñ","N") ))>0, "R", "" ) )} | I135: 0 | J135: {=IF( SUMPRODUCT(--( SUBSTITUTE(SUBSTITUTE(SUBSTITUTE(SUBSTITUTE(SUBSTITUTE(SUBSTITUTE(SUBSTITUTE( UPPER(TRIM(CLEAN(SUBSTITUTE(Hoja2!A$3:A$89,CHAR(160)," ")))), "Á","A"),"É","E"),"Í","I"),"Ó","O"),"Ú","U"),"Ü","U"),"Ñ","N") = SUBSTITUTE(SUBSTITUTE(SUBSTITUTE(SUBSTITUTE(SUBSTITUTE(SUBSTITUTE(SUBSTITUTE( UPPER(TRIM(CLEAN(SUBSTITUTE(I135,CHAR(160)," ")))), "Á","A"),"É","E"),"Í","I"),"Ó","O"),"Ú","U"),"Ü","U"),"Ñ","N") ))>0, "D", IF( SUMPRODUCT(--( SUBSTITUTE(SUBSTITUTE(SUBSTITUTE(SUBSTITUTE(SUBSTITUTE(SUBSTITUTE(SUBSTITUTE( UPPER(TRIM(CLEAN(SUBSTITUTE(Hoja2!A$92:A$154,CHAR(160)," ")))), "Á","A"),"É","E"),"Í","I"),"Ó","O"),"Ú","U"),"Ü","U"),"Ñ","N") = SUBSTITUTE(SUBSTITUTE(SUBSTITUTE(SUBSTITUTE(SUBSTITUTE(SUBSTITUTE(SUBSTITUTE( UPPER(TRIM(CLEAN(SUBSTITUTE(I135,CHAR(160)," ")))), "Á","A"),"É","E"),"Í","I"),"Ó","O"),"Ú","U"),"Ü","U"),"Ñ","N") ))>0, "R", "" ) )}
G136: =B136 -> 0 | H136: {=IF( SUMPRODUCT(--( SUBSTITUTE(SUBSTITUTE(SUBSTITUTE(SUBSTITUTE(SUBSTITUTE(SUBSTITUTE(SUBSTITUTE( UPPER(TRIM(CLEAN(SUBSTITUTE(Hoja2!A$3:A$89,CHAR(160)," ")))), "Á","A"),"É","E"),"Í","I"),"Ó","O"),"Ú","U"),"Ü","U"),"Ñ","N") = SUBSTITUTE(SUBSTITUTE(SUBSTITUTE(SUBSTITUTE(SUBSTITUTE(SUBSTITUTE(SUBSTITUTE( UPPER(TRIM(CLEAN(SUBSTITUTE(G136,CHAR(160)," ")))), "Á","A"),"É","E"),"Í","I"),"Ó","O"),"Ú","U"),"Ü","U"),"Ñ","N") ))>0, "D", IF( SUMPRODUCT(--( SUBSTITUTE(SUBSTITUTE(SUBSTITUTE(SUBSTITUTE(SUBSTITUTE(SUBSTITUTE(SUBSTITUTE( UPPER(TRIM(CLEAN(SUBSTITUTE(Hoja2!A$92:A$154,CHAR(160)," ")))), "Á","A"),"É","E"),"Í","I"),"Ó","O"),"Ú","U"),"Ü","U"),"Ñ","N") = SUBSTITUTE(SUBSTITUTE(SUBSTITUTE(SUBSTITUTE(SUBSTITUTE(SUBSTITUTE(SUBSTITUTE( UPPER(TRIM(CLEAN(SUBSTITUTE(G136,CHAR(160)," ")))), "Á","A"),"É","E"),"Í","I"),"Ó","O"),"Ú","U"),"Ü","U"),"Ñ","N") ))>0, "R", "" ) )} | I136: 0 | J136: {=IF( SUMPRODUCT(--( SUBSTITUTE(SUBSTITUTE(SUBSTITUTE(SUBSTITUTE(SUBSTITUTE(SUBSTITUTE(SUBSTITUTE( UPPER(TRIM(CLEAN(SUBSTITUTE(Hoja2!A$3:A$89,CHAR(160)," ")))), "Á","A"),"É","E"),"Í","I"),"Ó","O"),"Ú","U"),"Ü","U"),"Ñ","N") = SUBSTITUTE(SUBSTITUTE(SUBSTITUTE(SUBSTITUTE(SUBSTITUTE(SUBSTITUTE(SUBSTITUTE( UPPER(TRIM(CLEAN(SUBSTITUTE(I136,CHAR(160)," ")))), "Á","A"),"É","E"),"Í","I"),"Ó","O"),"Ú","U"),"Ü","U"),"Ñ","N") ))>0, "D", IF( SUMPRODUCT(--( SUBSTITUTE(SUBSTITUTE(SUBSTITUTE(SUBSTITUTE(SUBSTITUTE(SUBSTITUTE(SUBSTITUTE( UPPER(TRIM(CLEAN(SUBSTITUTE(Hoja2!A$92:A$154,CHAR(160)," ")))), "Á","A"),"É","E"),"Í","I"),"Ó","O"),"Ú","U"),"Ü","U"),"Ñ","N") = SUBSTITUTE(SUBSTITUTE(SUBSTITUTE(SUBSTITUTE(SUBSTITUTE(SUBSTITUTE(SUBSTITUTE( UPPER(TRIM(CLEAN(SUBSTITUTE(I136,CHAR(160)," ")))), "Á","A"),"É","E"),"Í","I"),"Ó","O"),"Ú","U"),"Ü","U"),"Ñ","N") ))>0, "R", "" ) )}
... G139: =B139 -> 0 | H139: {=IF( SUMPRODUCT(--( SUBSTITUTE(SUBSTITUTE(SUBSTITUTE(SUBSTITUTE(SUBSTITUTE(SUBSTITUTE(SUBSTITUTE( UPPER(TRIM(CLEAN(SUBSTITUTE(Hoja2!A$3:A$89,CHAR(160)," ")))), "Á","A"),"É","E"),"Í","I"),"Ó","O"),"Ú","U"),"Ü","U"),"Ñ","N") = SUBSTITUTE(SUBSTITUTE(SUBSTITUTE(SUBSTITUTE(SUBSTITUTE(SUBSTITUTE(SUBSTITUTE( UPPER(TRIM(CLEAN(SUBSTITUTE(G139,CHAR(160)," ")))), "Á","A"),"É","E"),"Í","I"),"Ó","O"),"Ú","U"),"Ü","U"),"Ñ","N") ))>0, "D", IF( SUMPRODUCT(--( SUBSTITUTE(SUBSTITUTE(SUBSTITUTE(SUBSTITUTE(SUBSTITUTE(SUBSTITUTE(SUBSTITUTE( UPPER(TRIM(CLEAN(SUBSTITUTE(Hoja2!A$92:A$154,CHAR(160)," ")))), "Á","A"),"É","E"),"Í","I"),"Ó","O"),"Ú","U"),"Ü","U"),"Ñ","N") = SUBSTITUTE(SUBSTITUTE(SUBSTITUTE(SUBSTITUTE(SUBSTITUTE(SUBSTITUTE(SUBSTITUTE( UPPER(TRIM(CLEAN(SUBSTITUTE(G139,CHAR(160)," ")))), "Á","A"),"É","E"),"Í","I"),"Ó","O"),"Ú","U"),"Ü","U"),"Ñ","N") ))>0, "R", "" ) )} | I139: 0 | J139: {=IF( SUMPRODUCT(--( SUBSTITUTE(SUBSTITUTE(SUBSTITUTE(SUBSTITUTE(SUBSTITUTE(SUBSTITUTE(SUBSTITUTE( UPPER(TRIM(CLEAN(SUBSTITUTE(Hoja2!A$3:A$89,CHAR(160)," ")))), "Á","A"),"É","E"),"Í","I"),"Ó","O"),"Ú","U"),"Ü","U"),"Ñ","N") = SUBSTITUTE(SUBSTITUTE(SUBSTITUTE(SUBSTITUTE(SUBSTITUTE(SUBSTITUTE(SUBSTITUTE( UPPER(TRIM(CLEAN(SUBSTITUTE(I139,CHAR(160)," ")))), "Á","A"),"É","E"),"Í","I"),"Ó","O"),"Ú","U"),"Ü","U"),"Ñ","N") ))>0, "D", IF( SUMPRODUCT(--( SUBSTITUTE(SUBSTITUTE(SUBSTITUTE(SUBSTITUTE(SUBSTITUTE(SUBSTITUTE(SUBSTITUTE( UPPER(TRIM(CLEAN(SUBSTITUTE(Hoja2!A$92:A$154,CHAR(160)," ")))), "Á","A"),"É","E"),"Í","I"),"Ó","O"),"Ú","U"),"Ü","U"),"Ñ","N") = SUBSTITUTE(SUBSTITUTE(SUBSTITUTE(SUBSTITUTE(SUBSTITUTE(SUBSTITUTE(SUBSTITUTE( UPPER(TRIM(CLEAN(SUBSTITUTE(I139,CHAR(160)," ")))), "Á","A"),"É","E"),"Í","I"),"Ó","O"),"Ú","U"),"Ü","U"),"Ñ","N") ))>0, "R", "" ) )}
...

Sheet pareto
A1: categoria | B1: descriptor | C1: Frecuencia | D1: porcentaje | E1: Acumulado | F1: acumulado | G1: segmento

Sheet Hoja2
A2: Delitos | B2: Delitos
A3: ABANDONO DE PERSONAS (MENOR DE EDAD, ADULTO MAYOR O CON CAPACIDADES DIFERENTES) | B3: ABANDONO DE PERSONAS (MENOR DE EDAD, ADULTO MAYOR O CON CAPACIDADES DIFERENTES)
A4: ABIGEATO (ROBO Y DESTACE DE GANADO) | B4: ABIGEATO (ROBO Y DESTACE DE GANADO)
A5: ABORTO | B5: ABORTO
A6: ABUSO DE AUTORIDAD | B6: ABUSO DE AUTORIDAD
A7: ACCIONAMIENTO DE ARMA DE FUEGO (BALACERAS) | B7: ACCIONAMIENTO DE ARMA DE FUEGO (BALACERAS)
A8: ADMINISTRACION FRAUDULENTA, APROPIACIONES INDEBIDAS O ENRIQUECIMIENTO ILICITO | B8: ADMINISTRACION FRAUDULENTA, APROPIACIONES INDEBIDAS O ENRIQUECIMIENTO ILICITO
A9: AGRESION CON ARMAS | B9: AGRESION CON ARMAS
A10: ALTERACION DE DATOS Y SABOTAJE INFORMATICO | B10: ALTERACION DE DATOS Y SABOTAJE INFORMATICO
A11: AMENAZAS | B11: AMENAZAS
A12: CALUMNIA | B12: CALUMNIA
A13: CAZA ILEGAL | B13: CAZA ILEGAL
... A256: Pococí Norte | B256: D98
